flask_modular_login/__init__.py
flask_modular_login/access.py
flask_modular_login/builder.py
flask_modular_login/endpoints.py
flask_modular_login/group.py
flask_modular_login/interface.py
flask_modular_login/platforms.py
flask_modular_login/pubsub.py
flask_modular_login/server.py
flask_modular_login/store.py
flask_modular_login/test.py
flask_modular_login/tokens.py
flask_modular_login/utils.py
flask_modular_login-0.1.1.dist-info/METADATA
flask_modular_login-0.1.1.dist-info/WHEEL
flask_modular_login-0.1.1.dist-info/top_level.txt
flask_modular_login-0.1.1.dist-info/RECORD
