Metadata-Version: 2.1
Name: flask-modular-login
Version: 0.1.1
Summary: A modular login framework for Flask
Requires-Dist: wheel
Requires-Dist: flask
Requires-Dist: flask-dance
Requires-Dist: blinker
Requires-Dist: flask-caching
Requires-Dist: uwsgi
Requires-Dist: libmc
Requires-Dist: cryptography
Requires-Dist: requests
Requires-Dist: websockets
